Workbook

Sheet Dashboard
B1: 🏢 CLOUD-BASED BILLING, INVENTORY & ACCOUNTING ERP SUITE • EXECUTIVE DASHBOARD
B2: TOTAL INVENTORY VALUE | E2: LOW STOCK & ZERO STOCK ALERTS | H2: ACCOUNTS RECEIVABLE (TO COLLECT) | L2: ACCOUNTS PAYABLE (TO PAY)
B3: =SUM(Inventory_Master!P2:P100) | E3: =COUNTIF(Inventory_Master!Q2:Q100, "Low Stock") + COUNTIF(Inventory_Master!Q2:Q100, "Out of Stock") | H3: =IFERROR(__xludf.DUMMYFUNCTION("IFERROR(SUMPRODUCT((Parties_Directory!C2:C100=""Customer"") * IFERROR(REGEXREPLACE(Parties_Directory!D2:D100&"""", ""[^0-9.-]"", """")+0, 0)), 0)"),132370.169999999) | L3: =IFERROR(__xludf.DUMMYFUNCTION("IFERROR(SUMPRODUCT((Parties_Directory!C2:C100=""Supplier"") * IFERROR(REGEXREPLACE(Parties_Directory!D2:D100&"""", ""[^0-9.-]"", """")+0, 0)), 0)"),62531.59)
B5: =COUNTA(Inventory_Master!A2:A100)&" Total Catalog Products" | E5: ="Critical: "&COUNTIF(Inventory_Master!Q2:Q100, "Out of Stock")&" Zero Stock Items" | H5: =IFERROR(__xludf.DUMMYFUNCTION("SUMPRODUCT((Parties_Directory!C2:C100=""Customer"") * (IFERROR(REGEXREPLACE(Parties_Directory!D2:D100&"""", ""[^0-9.-]"", """")+0, 0) > 0)) & "" Customers with Pending Balance"""),"7 Customers with Pending Balance") | L5: =IFERROR(__xludf.DUMMYFUNCTION("SUMPRODUCT((Parties_Directory!C2:C100=""Supplier"") * (IFERROR(REGEXREPLACE(Parties_Directory!D2:D100&"""", ""[^0-9.-]"", """")+0, 0) > 0)) & "" Suppliers with Pending Balance"""),"2 Suppliers with Pending Balance")
B7: 📦 INVENTORY CATEGORY ANALYSIS & ASSET ALLOCATION | I7: ⚠️ STOCK HEALTH & RESTOCK PRIORITY MONITOR
B8: Category Name | C8: Items Count | D8: Units on Hand | E8: Stock Value (₹) | F8: Avg Unit Cost | G8: Share % | I8: Stock Condition | J8: Items Count | K8: Catalog Share | L8: Units Total | M8: Valuation (₹) | N8: Recommended Action | O8: Alert Level
B9: Electronics | C9: =COUNTIF(Inventory_Master!$C$2:$C100, B9) | D9: =SUMIF(Inventory_Master!$C$2:$C100, B9, Inventory_Master!$L$2:$L100) | E9: =SUMIF(Inventory_Master!$C$2:$C100, B9, Inventory_Master!$P$2:$P100) | F9: =IFERROR(E9/D9, 0) | G9: =IFERROR(E9/$E$28, 0) | I9: In Stock (Healthy) | J9: =COUNTIF(Inventory_Master!$Q$2:$Q100, "In Stock") | K9: =IFERROR(J9/$J$12, 0) | L9: =SUMIF(Inventory_Master!$Q$2:$Q100, "In Stock", Inventory_Master!$L$2:$L100) | M9: =SUMIF(Inventory_Master!$Q$2:$Q100, "In Stock", Inventory_Master!$P$2:$P100) | N9: Sufficient Inventory | O9: Normal
B10: Kerala Clothing | C10: =COUNTIF(Inventory_Master!$C$2:$C100, B10) | D10: =SUMIF(Inventory_Master!$C$2:$C100, B10, Inventory_Master!$L$2:$L100) | E10: =SUMIF(Inventory_Master!$C$2:$C100, B10, Inventory_Master!$P$2:$P100) | F10: =IFERROR(E10/D10, 0) | G10: =IFERROR(E10/$E$28, 0) | I10: Low Stock (Reorder) | J10: =COUNTIF(Inventory_Master!$Q$2:$Q100, "Low Stock") | K10: =IFERROR(J10/$J$12, 0) | L10: =SUMIF(Inventory_Master!$Q$2:$Q100, "Low Stock", Inventory_Master!$L$2:$L100) | M10: =SUMIF(Inventory_Master!$Q$2:$Q100, "Low Stock", Inventory_Master!$P$2:$P100) | N10: Create Restock PO | O10: Warning
B11: Kitchen Utensils | C11: =COUNTIF(Inventory_Master!$C$2:$C100, B11) | D11: =SUMIF(Inventory_Master!$C$2:$C100, B11, Inventory_Master!$L$2:$L100) | E11: =SUMIF(Inventory_Master!$C$2:$C100, B11, Inventory_Master!$P$2:$P100) | F11: =IFERROR(E11/D11, 0) | G11: =IFERROR(E11/$E$28, 0) | I11: Out of Stock (Zero) | J11: =COUNTIF(Inventory_Master!$Q$2:$Q100, "Out of Stock") | K11: =IFERROR(J11/$J$12, 0) | L11: 0 | M11: 0 | N11: Immediate Restock | O11: Critical
B12: Masalas & Spices | C12: =COUNTIF(Inventory_Master!$C$2:$C100, B12) | D12: =SUMIF(Inventory_Master!$C$2:$C100, B12, Inventory_Master!$L$2:$L100) | E12: =SUMIF(Inventory_Master!$C$2:$C100, B12, Inventory_Master!$P$2:$P100) | F12: =IFERROR(E12/D12, 0) | G12: =IFERROR(E12/$E$28, 0) | I12: All Status Total | J12: =SUM(J9:J11) | K12: =SUM(K9:K11) | L12: =SUM(L9:L11) | M12: =SUM(M9:M11) | N12: System Monitored | O12: 100%
B13: Pickles | C13: =COUNTIF(Inventory_Master!$C$2:$C100, B13) | D13: =SUMIF(Inventory_Master!$C$2:$C100, B13, Inventory_Master!$L$2:$L100) | E13: =SUMIF(Inventory_Master!$C$2:$C100, B13, Inventory_Master!$P$2:$P100) | F13: =IFERROR(E13/D13, 0) | G13: =IFERROR(E13/$E$28, 0)
B14: Snacks | C14: =COUNTIF(Inventory_Master!$C$2:$C100, B14) | D14: =SUMIF(Inventory_Master!$C$2:$C100, B14, Inventory_Master!$L$2:$L100) | E14: =SUMIF(Inventory_Master!$C$2:$C100, B14, Inventory_Master!$P$2:$P100) | F14: =IFERROR(E14/D14, 0) | G14: =IFERROR(E14/$E$28, 0)
B15: Raw Items & Produce | C15: =COUNTIF(Inventory_Master!$C$2:$C100, B15) | D15: =SUMIF(Inventory_Master!$C$2:$C100, B15, Inventory_Master!$L$2:$L100) | E15: =SUMIF(Inventory_Master!$C$2:$C100, B15, Inventory_Master!$P$2:$P100) | F15: =IFERROR(E15/D15, 0) | G15: =IFERROR(E15/$E$28, 0)
B16: Books & Bibles | C16: =COUNTIF(Inventory_Master!$C$2:$C100, B16) | D16: =SUMIF(Inventory_Master!$C$2:$C100, B16, Inventory_Master!$L$2:$L100) | E16: =SUMIF(Inventory_Master!$C$2:$C100, B16, Inventory_Master!$P$2:$P100) | F16: =IFERROR(E16/D16, 0) | G16: =IFERROR(E16/$E$28, 0)
B17: Healthcare Items | C17: =COUNTIF(Inventory_Master!$C$2:$C100, B17) | D17: =SUMIF(Inventory_Master!$C$2:$C100, B17, Inventory_Master!$L$2:$L100) | E17: =SUMIF(Inventory_Master!$C$2:$C100, B17, Inventory_Master!$P$2:$P100) | F17: =IFERROR(E17/D17, 0) | G17: =IFERROR(E17/$E$28, 0)
B18: Grains & Flours | C18: =COUNTIF(Inventory_Master!$C$2:$C100, B18) | D18: =SUMIF(Inventory_Master!$C$2:$C100, B18, Inventory_Master!$L$2:$L100) | E18: =SUMIF(Inventory_Master!$C$2:$C100, B18, Inventory_Master!$P$2:$P100) | F18: =IFERROR(E18/D18, 0) | G18: =IFERROR(E18/$E$28, 0)
B19: Rice Items | C19: =COUNTIF(Inventory_Master!$C$2:$C100, B19) | D19: =SUMIF(Inventory_Master!$C$2:$C100, B19, Inventory_Master!$L$2:$L100) | E19: =SUMIF(Inventory_Master!$C$2:$C100, B19, Inventory_Master!$P$2:$P100) | F19: =IFERROR(E19/D19, 0) | G19: =IFERROR(E19/$E$28, 0)
B20: Edible Oils & Ghee | C20: =COUNTIF(Inventory_Master!$C$2:$C100, B20) | D20: =SUMIF(Inventory_Master!$C$2:$C100, B20, Inventory_Master!$L$2:$L100) | E20: =SUMIF(Inventory_Master!$C$2:$C100, B20, Inventory_Master!$P$2:$P100) | F20: =IFERROR(E20/D20, 0) | G20: =IFERROR(E20/$E$28, 0)
B21: Fish & Meat | C21: =COUNTIF(Inventory_Master!$C$2:$C100, B21) | D21: =SUMIF(Inventory_Master!$C$2:$C100, B21, Inventory_Master!$L$2:$L100) | E21: =SUMIF(Inventory_Master!$C$2:$C100, B21, Inventory_Master!$P$2:$P100) | F21: =IFERROR(E21/D21, 0) | G21: =IFERROR(E21/$E$28, 0)
B22: Ready to Eat & Mixes | C22: =COUNTIF(Inventory_Master!$C$2:$C100, B22) | D22: =SUMIF(Inventory_Master!$C$2:$C100, B22, Inventory_Master!$L$2:$L100) | E22: =SUMIF(Inventory_Master!$C$2:$C100, B22, Inventory_Master!$P$2:$P100) | F22: =IFERROR(E22/D22, 0) | G22: =IFERROR(E22/$E$28, 0)
B23: Beverages | C23: =COUNTIF(Inventory_Master!$C$2:$C100, B23) | D23: =SUMIF(Inventory_Master!$C$2:$C100, B23, Inventory_Master!$L$2:$L100) | E23: =SUMIF(Inventory_Master!$C$2:$C100, B23, Inventory_Master!$P$2:$P100) | F23: =IFERROR(E23/D23, 0) | G23: =IFERROR(E23/$E$28, 0)
B24: Church Articles | C24: =COUNTIF(Inventory_Master!$C$2:$C100, B24) | D24: =SUMIF(Inventory_Master!$C$2:$C100, B24, Inventory_Master!$L$2:$L100) | E24: =SUMIF(Inventory_Master!$C$2:$C100, B24, Inventory_Master!$P$2:$P100) | F24: =IFERROR(E24/D24, 0) | G24: =IFERROR(E24/$E$28, 0)
B25: Stationery | C25: =COUNTIF(Inventory_Master!$C$2:$C100, B25) | D25: =SUMIF(Inventory_Master!$C$2:$C100, B25, Inventory_Master!$L$2:$L100) | E25: =SUMIF(Inventory_Master!$C$2:$C100, B25, Inventory_Master!$P$2:$P100) | F25: =IFERROR(E25/D25, 0) | G25: =IFERROR(E25/$E$28, 0)
B26: Fixed Assets | C26: =COUNTIF(Inventory_Master!$C$2:$C100, B26) | D26: =SUMIF(Inventory_Master!$C$2:$C100, B26, Inventory_Master!$L$2:$L100) | E26: =SUMIF(Inventory_Master!$C$2:$C100, B26, Inventory_Master!$P$2:$P100) | F26: =IFERROR(E26/D26, 0) | G26: =IFERROR(E26/$E$28, 0)
B27: Household & Cleaning | C27: =COUNTIF(Inventory_Master!$C$2:$C100, B27) | D27: =SUMIF(Inventory_Master!$C$2:$C100, B27, Inventory_Master!$L$2:$L100) | E27: =SUMIF(Inventory_Master!$C$2:$C100, B27, Inventory_Master!$P$2:$P100) | F27: =IFERROR(E27/D27, 0) | G27: =IFERROR(E27/$E$28, 0)
B28: Total Inventory | C28: =SUM(C9:C27) | D28: =SUM(D9:D27) | E28: =SUM(E9:E27) | F28: =IFERROR(E28/D28, 0) | G28: =SUM(G9:G27)

Sheet Inventory_Master
A1: Item Name* (mandatory field) | B1: Description | C1: Category | D1: Item code | E1: HSN Code | F1: GST Tax Rate(%) | G1: Sales Price | H1: Sales Tax inclusive | I1: Purchase Price | J1: Purchase Tax inclusive | K1: MRP | L1: Current stock | M1: Low stock alert quantity | N1: Visible on Online Store? | O1: Discount | P1: Stock Valuation | Q1: Stock Status Alert
A2: 120W TYPE C CABLE | C2: Electronics | D2: 514182562487 | F2: 0 | G2: 60 | H2: Exclusive | I2: 30 | J2: Exclusive | K2: 90 | L2: 14 | N2: Yes | O2: 0 | P2: 420 | Q2: In Stock
A3: 128 GB MEMORY CARD | C3: Electronics | D3: 100001 | F3: 0 | G3: 640 | H3: Inclusive | I3: 250 | J3: Inclusive | K3: 720 | L3: 0 | M3: 1 | N3: No | O3: 0 | P3: 450 | Q3: In Stock
A4: 16GB MEMORY CARD | C4: Electronics | D4: 100002 | F4: 0 | G4: 270 | H4: Inclusive | I4: 170 | J4: Inclusive | K4: 300 | L4: 1 | M4: 1 | N4: No | O4: 0 | P4: 450 | Q4: In Stock
A5: 32GB MEMORY CARD | C5: Electronics | D5: 100003 | F5: 0 | G5: 370 | H5: Inclusive | I5: 210 | J5: Inclusive | K5: 420 | L5: 0 | M5: 1 | N5: No | O5: 0 | P5: 450 | Q5: In Stock
A6: 32GB PENDRIVE | C6: Electronics | D6: 284487757003 | F6: 0 | G6: 485 | H6: Exclusive | I6: 270 | J6: Exclusive | K6: 525 | L6: 5 | N6: Yes | O6: 0 | P6: 450 | Q6: In Stock
A7: 64 GB MEMORY CARD | C7: Electronics | D7: 100004 | F7: 0 | G7: 470 | H7: Inclusive | I7: 230 | J7: Inclusive | K7: 520 | L7: 0 | M7: 1 | N7: No | O7: 0 | P7: 450 | Q7: In Stock
A8: 999 KARA MUND | C8: Kerala Clothing | D8: 321028977531 | F8: 0 | G8: 380 | H8: Inclusive | I8: 290 | J8: Inclusive | K8: 400 | L8: 0 | M8: 1 | N8: Yes | O8: 0 | P8: 450 | Q8: In Stock
A9: 9 PC GIFT MIX | C9: Church Articles | D9: 406295139484 | F9: 0 | G9: 50 | H9: Exclusive | I9: 36 | J9: Inclusive | K9: 50 | L9: 0 | M9: 1 | N9: Yes | O9: 0 | P9: 450 | Q9: In Stock
A10: A3 LAMINATION | C10: Stationery | D10: LA3 | F10: 0 | G10: 30 | H10: Inclusive | I10: 10 | J10: Inclusive | K10: 40 | L10: 407 | M10: 1 | N10: No | O10: 0 | P10: 450 | Q10: In Stock
A11: A3 WALL TEXT WITHOUT LAMINATION | C11: Church Articles | D11: 100005 | F11: 0 | G11: 30 | H11: Exclusive | I11: 20 | J11: Exclusive | K11: 35 | L11: 4 | M11: 1 | N11: No | O11: 0 | P11: 450 | Q11: In Stock
A12: A4 FRAME WITH WALL TEXT | C12: Church Articles | D12: 352219848557 | F12: 0 | G12: 200 | H12: Inclusive | I12: 150 | J12: Inclusive | K12: 220 | L12: 0 | M12: 1 | N12: No | O12: 0 | P12: 450 | Q12: In Stock
A13: A4 GLOSSY PAPER | C13: Stationery | D13: 100006 | F13: 0 | G13: 6 | H13: Inclusive | I13: 3 | J13: Inclusive | K13: 7 | L13: 1000 | M13: 1 | N13: No | O13: 0 | P13: 450 | Q13: In Stock
A14: A4 LAMINATION | C14: Stationery | D14: 100007 | F14: 0 | G14: 20 | H14: Inclusive | I14: 9 | J14: Inclusive | K14: 25 | L14: 178 | M14: 1 | N14: No | O14: 0 | P14: 450 | Q14: In Stock
A15: A4 PAPER BUNDLE | C15: Stationery | D15: 100008 | F15: 0 | G15: 240 | H15: Exclusive | I15: 210 | J15: Exclusive | K15: 322 | L15: 0 | M15: 1 | N15: No | O15: 0 | P15: 450 | Q15: In Stock
A16: A4 SINGLE SHEET | C16: Stationery | D16: 100009 | F16: 0 | G16: 1 | H16: Exclusive | I16: 0.5 | J16: Exclusive | K16: 2 | L16: 0 | M16: 1 | N16: No | O16: 0 | P16: 450 | Q16: In Stock
A17: AACHI CHICKEN 65 50GM | C17: Masalas & Spices | D17: 8906021120418 | F17: 0 | G17: 32 | H17: Inclusive | I17: 24 | J17: Inclusive | K17: 32 | L17: 0 | M17: 1 | N17: Yes | O17: 0 | P17: 450 | Q17: In Stock
A18: AACHI FISH CURRY MASALA 550GM | C18: Masalas & Spices | D18: 100010 | F18: 0 | G18: 52 | H18: Inclusive | I18: 19 | J18: Inclusive | K18: 0 | L18: 4 | M18: 1 | N18: Yes | O18: 0 | P18: 450 | Q18: In Stock
... A26: AGRAHAR VADUKAPULI PICKLE 200GM | C26: Pickles | D26: 100015 | F26: 0 | G26: 80 | H26: Exclusive | I26: 72 | J26: Exclusive | K26: 0 | L26: 0 | M26: 1 | N26: Yes | O26: 0 | P26: 450 | Q26: In Stock
A27: AIRCONDITIONER | C27: Fixed Assets | D27: 100016 | F27: 0 | G27: 12000 | H27: Exclusive | I27: 12000 | J27: Exclusive | K27: 12000 | L27: 0 | N27: Yes | O27: 0 | P27: 450 | Q27: In Stock
A28: AJWA ANDHRA MURUK WHITE 60/- | C28: Snacks | D28: 8906054683430 | F28: 0 | G28: 60 | H28: Exclusive | I28: 44 | J28: Exclusive | K28: 60 | L28: 0 | M28: 1 | N28: Yes | O28: 0 | P28: 450 | Q28: In Stock
A29: AJWA BUTTER MURUK SMALL | C29: Snacks | D29: 942174962478 | F29: 0 | G29: 70 | H29: Exclusive | I29: 55 | J29: Exclusive | K29: 70 | L29: 32 | M29: 1 | N29: Yes | O29: 0 | P29: 450 | Q29: In Stock
A30: AJWA BUTTER MURUK SPICY | C30: Snacks | D30: 8906054688022 | F30: 0 | G30: 75 | H30: Exclusive | I30: 60 | J30: Exclusive | K30: 75 | L30: 24 | M30: 1 | N30: Yes | O30: 0 | P30: 450 | Q30: In Stock
A31: AJWA BUTTER MURUK SPICY 60/- | C31: Snacks | D31: 8906054688251 | F31: 0 | G31: 70 | H31: Exclusive | I31: 50 | J31: Exclusive | K31: 70 | L31: 0 | M31: 1 | N31: Yes | O31: 0 | P31: 450 | Q31: In Stock
A32: AJWA GARLIC MURUK | C32: Snacks | D32: 8906054683416 | F32: 0 | G32: 80 | H32: Exclusive | I32: 44 | J32: Exclusive | K32: 60 | L32: 3 | M32: 1 | N32: Yes | O32: 0 | P32: 450 | Q32: In Stock
A33: AJWA ROLL MURUK | C33: Snacks | D33: 8906054688183 | F33: 0 | G33: 75 | H33: Inclusive | I33: 50 | J33: Inclusive | K33: 75 | L33: 0 | M33: 1 | N33: Yes | O33: 0 | P33: 450 | Q33: In Stock
A34: ALMIRAH MAKING | C34: Fixed Assets | D34: 100017 | F34: 0 | G34: 23000 | H34: Exclusive | I34: 23000 | J34: Exclusive | K34: 23000 | L34: 1 | M34: 1 | N34: No | O34: 0 | P34: 450 | Q34: In Stock
A35: ALO FRUIT 3 DEGREE MINT | C35: Beverages | D35: 8906044995963 | F35: 0 | G35: 60 | H35: Exclusive | I35: 52 | J35: Exclusive | K35: 60 | L35: 3 | M35: 1 | N35: Yes | O35: 0 | P35: 450 | Q35: In Stock
A36: AMMA VADI MATTA RICE 5KG | C36: Rice Items | D36: 8908882426067 | F36: 0 | G36: 520 | H36: Exclusive | I36: 333.33 | J36: Exclusive | K36: 520 | L36: 0 | N36: Yes | O36: 0 | P36: 450 | Q36: In Stock
A37: AMUL KOOL 200GM | C37: Beverages | D37: 8901262152211 | F37: 0 | G37: 25 | H37: Exclusive | I37: 23 | J37: Exclusive | K37: 25 | L37: 0 | M37: 1 | N37: Yes | O37: 0 | P37: 450 | Q37: In Stock
A38: ANANT JEEVAN | C38: Books & Bibles | D38: 100018 | F38: 0 | G38: 50 | H38: Exclusive | I38: 30 | J38: Exclusive | K38: 80 | L38: 0 | M38: 1 | N38: Yes | O38: 0 | P38: 450 | Q38: In Stock
A39: ANCHOVY ACHAR | C39: Pickles | D39: 8907093003111 | F39: 0 | G39: 225 | H39: Exclusive | I39: 216 | J39: Exclusive | K39: 225 | L39: 0 | M39: 1 | N39: Yes | O39: 0 | P39: 450 | Q39: In Stock
A40: ANDERSON PUZZLE BOOK ENGLISH | C40: Books & Bibles | D40: 100019 | F40: 0 | G40: 250 | H40: Exclusive | I40: 110 | J40: Exclusive | K40: 280 | L40: 3 | M40: 1 | N40: Yes | O40: 0 | P40: 450 | Q40: In Stock
A41: ANUS FIED RAWA 500GM | C41: Grains & Flours | D41: 8904406128387 | F41: 0 | G41: 58 | H41: Exclusive | I41: 56 | J41: Exclusive | K41: 0 | L41: 0 | M41: 1 | N41: Yes | O41: 0 | P41: 450 | Q41: In Stock
A42: ANUS GINGER COFFEE 150GM | C42: Beverages | D42: 8904406127182 | F42: 0 | G42: 105 | H42: Exclusive | I42: 95 | J42: Exclusive | K42: 105 | L42: 4 | M42: 1 | N42: Yes | O42: 0 | P42: 450 | Q42: In Stock
A43: ANUS KUTTANADAN BIRYANI MIX | C43: Ready to Eat & Mixes | D43: 8904406126888 | F43: 0 | G43: 295 | H43: Inclusive | I43: 260 | J43: Inclusive | K43: 295 | L43: 0 | M43: 1 | N43: Yes | O43: 0 | P43: 450 | Q43: In Stock
A44: ANUS LEMON PICKLE 500GM | C44: Pickles | D44: 100020 | F44: 0 | G44: 84 | H44: Exclusive | I44: 75 | J44: Exclusive | K44: 84 | L44: 0 | M44: 1 | N44: Yes | O44: 0 | P44: 450 | Q44: In Stock
A45: ANUS LIME PICKLE 500GM | C45: Pickles | D45: 100021 | F45: 0 | G45: 84 | H45: Exclusive | I45: 77 | J45: Exclusive | K45: 84 | L45: 2 | M45: 1 | N45: Yes | O45: 0 | P45: 450 | Q45: In Stock
A46: ANUS PALADA MIX | C46: Ready to Eat & Mixes | D46: 8904406126819 | F46: 0 | G46: 75 | H46: Exclusive | I46: 74 | J46: Exclusive | K46: 75 | L46: 1 | M46: 1 | N46: Yes | O46: 0 | P46: 450 | Q46: In Stock
A47: ANUS PULI TAMARIND 250 | C47: Masalas & Spices | D47: 8904406127441 | F47: 0 | G47: 50 | H47: Exclusive | I47: 45 | J47: Exclusive | K47: 50 | L47: 0 | M47: 1 | N47: Yes | O47: 0 | P47: 450 | Q47: In Stock
A48: ANUS SABUDANA CHOWARY 100GM | C48: Grains & Flours | D48: 8904406127281 | F48: 0 | G48: 23 | H48: Exclusive | I48: 20 | J48: Exclusive | K48: 23 | L48: 0 | M48: 1 | N48: Yes | O48: 0 | P48: 450 | Q48: In Stock
... A69: BANANA CHIPS SMALL SLICE 250GM | C69: Snacks | D69: 501955159733 | F69: 0 | G69: 140 | H69: Exclusive | I69: 100 | J69: Exclusive | K69: 150 | L69: 0 | M69: 1 | N69: Yes | O69: 0 | P69: 450 | Q69: In Stock
A70: BASUMATI RICE 1KG | C70: Rice Items | D70: 8906007287012 | F70: 0 | G70: 149 | H70: Exclusive | I70: 116 | J70: Exclusive | K70: 169 | L70: 2 | N70: Yes | O70: 0 | P70: 450 | Q70: In Stock
A71: BASUMATI RICE 1KG | C71: Rice Items | D71: 202838303039 | F71: 0 | G71: 136 | H71: Exclusive | I71: 118 | J71: Exclusive | K71: 152 | L71: 0 | M71: 1 | N71: Yes | O71: 0 | P71: 450 | Q71: In Stock
A72: BB COOKIES | C72: Snacks | D72: 1000000125 | F72: 0 | G72: 190 | H72: Exclusive | I72: 180 | J72: Exclusive | K72: 190 | L72: 0 | M72: 1 | N72: Yes | O72: 0 | P72: 450 | Q72: In Stock
A73: BEANS KADALA - MATTAR 500GM | C73: Grains & Flours | D73: 413121627918 | F73: 0 | G73: 38 | H73: Exclusive | I73: 28 | J73: Exclusive | K73: 42 | L73: 1 | M73: 1 | N73: Yes | O73: 0 | P73: 450 | Q73: In Stock
A74: BELL TYPE KEYCHAIN | C74: Church Articles | D74: 307588940274 | F74: 0 | G74: 30 | H74: Exclusive | I74: 18 | J74: Exclusive | K74: 40 | L74: 10 | N74: Yes | O74: 0 | P74: 450 | Q74: In Stock
A75: BIBLE AND GEETA | C75: Books & Bibles | D75: 100031 | F75: 0 | G75: 80 | H75: Inclusive | I75: 70 | J75: Inclusive | K75: 100 | L75: 4 | M75: 1 | N75: Yes | O75: 0 | P75: 450 | Q75: In Stock
A76: BIBLE BILINGUAL - HINDI ENGLISH | C76: Books & Bibles | D76: 451195934499 | F76: 0 | G76: 2200 | H76: Inclusive | I76: 1800 | J76: Inclusive | K76: 2500 | L76: 1 | M76: 1 | N76: Yes | O76: 0 | P76: 450 | Q76: In Stock
A77: BIBLE CHILDREN BALSULABH SACHITRA | C77: Books & Bibles | D77: 100032 | F77: 0 | G77: 500 | H77: Inclusive | I77: 315 | J77: Inclusive | K77: 700 | L77: 69 | M77: 1 | N77: Yes | O77: 0 | P77: 450 | Q77: In Stock
A78: BIBLE COVER GOOD QUALITY | C78: Church Articles | D78: 829352861043 | F78: 0 | G78: 220 | H78: Exclusive | I78: 105 | J78: Exclusive | K78: 250 | L78: 243 | M78: 1 | N78: Yes | O78: 0 | P78: 450 | Q78: In Stock
A79: BIBLE COVER LATEST | C79: Church Articles | D79: 552508580053 | F79: 0 | G79: 180 | H79: Inclusive | I79: 90 | J79: Inclusive | K79: 200 | L79: 0 | M79: 1 | N79: Yes | O79: 0 | P79: 450 | Q79: In Stock
A80: BIBLE GILT EDITION | C80: Books & Bibles | D80: 100033 | F80: 0 | G80: 600 | H80: Exclusive | I80: 370 | J80: Exclusive | K80: 750 | L80: 1 | M80: 1 | N80: Yes | O80: 0 | P80: 450 | Q80: In Stock
A81: BIBLE GREY EDGE | C81: Books & Bibles | D81: 100034 | F81: 0 | G81: 300 | H81: Exclusive | I81: 170 | J81: Exclusive | K81: 300 | L81: 55 | M81: 1 | N81: Yes | O81: 0 | P81: 450 | Q81: In Stock
A82: BIBLE KIDS VERSION ENGLISH | C82: Books & Bibles | D82: 100035 | F82: 0 | G82: 300 | H82: Inclusive | I82: 200 | J82: Inclusive | K82: 250 | L82: 0 | M82: 1 | N82: Yes | O82: 0 | P82: 450 | Q82: In Stock
A83: BIBLE KI KAHANIYAN HINDI | C83: Books & Bibles | D83: 100036 | F83: 0 | G83: 295 | H83: Inclusive | I83: 225 | J83: Inclusive | K83: 300 | L83: 0 | M83: 1 | N83: Yes | O83: 0 | P83: 450 | Q83: In Stock
A84: BIBLE KING JAMES VERSION ENGLISH | C84: Books & Bibles | D84: kjv | F84: 0 | G84: 300 | H84: Inclusive | I84: 280 | J84: Inclusive | K84: 400 | L84: 2 | M84: 1 | N84: Yes | O84: 0 | P84: 450 | Q84: In Stock
A85: BIBLE PAVITR OV | C85: Books & Bibles | D85: 300249770399 | F85: 0 | G85: 300 | H85: Inclusive | I85: 155 | J85: Inclusive | K85: 320 | L85: 0 | M85: 1 | N85: Yes | O85: 0 | P85: 450 | Q85: In Stock
A86: BIBLE SAMPOORNA ADYAYAN | C86: Books & Bibles | D86: 100037 | F86: 0 | G86: 1200 | H86: Inclusive | I86: 720 | J86: Inclusive | K86: 1650 | L86: 0 | M86: 1 | N86: Yes | O86: 0 | P86: 450 | Q86: In Stock
... A90: BIBLE WITHOUT INDEX | C90: Books & Bibles | D90: 313573166296 | F90: 0 | G90: 600 | H90: Exclusive | I90: 400 | J90: Exclusive | K90: 700 | L90: 11 | M90: 1 | N90: Yes | O90: 0 | P90: 450 | Q90: In Stock
A91: BIGGEST 3D WALL FRAME | C91: Church Articles | D91: 911616436182 | F91: 0 | G91: 900 | H91: Exclusive | I91: 750 | J91: Exclusive | K91: 1100 | L91: 0 | N91: Yes | O91: 0 | P91: 450 | Q91: In Stock
A92: BIG INDEX STUDY BIBLE WITH COVER | C92: Books & Bibles | D92: 100039 | F92: 0 | G92: 1500 | H92: Exclusive | I92: 1000 | J92: Exclusive | K92: 1800 | L92: 0 | M92: 1 | N92: Yes | O92: 0 | P92: 450 | Q92: In Stock
A93: BIRIYANI BASMATI RICE SPECIAL 1KG | C93: Rice Items | D93: 165672970442 | F93: 0 | G93: 122 | H93: Exclusive | I93: 62 | J93: Exclusive | K93: 129 | L93: 100 | M93: 1 | N93: Yes | O93: 0 | P93: 450 | Q93: In Stock
A94: BIRYANI ESSENCE | C94: Ready to Eat & Mixes | D94: 8907885001721 | F94: 0 | G94: 109 | H94: Exclusive | I94: 74 | J94: Exclusive | K94: 109 | L94: 0 | M94: 1 | N94: Yes | O94: 0 | P94: 450 | Q94: In Stock
A95: BITS DRINK 320ML - DIFFERENT FLAVOURS | C95: Beverages | D95: 8908013674268 | F95: 0 | G95: 70 | H95: Exclusive | I95: 50 | J95: Exclusive | K95: 70 | L95: 0 | M95: 1 | N95: Yes | O95: 0 | P95: 450 | Q95: In Stock
A96: BLACK PEPPER 500GM | C96: Masalas & Spices | D96: 458335769097 | F96: 0 | G96: 410 | H96: Exclusive | I96: 375 | J96: Exclusive | K96: 425 | L96: 0 | M96: 1 | N96: Yes | O96: 0 | P96: 450 | Q96: In Stock
A97: BLACK PEPPER (KURUMULAK)100GM | C97: Masalas & Spices | D97: 375640493824 | F97: 0 | G97: 160 | H97: Exclusive | I97: 92 | J97: Exclusive | K97: 120 | L97: 1 | M97: 1 | N97: Yes | O97: 0 | P97: 450 | Q97: In Stock
A98: BLACK PRINTING/COPYING | C98: Stationery | D98: 100040 | F98: 0 | G98: 5 | H98: Inclusive | I98: 1 | J98: Inclusive | K98: 5 | L98: 0 | M98: 1 | N98: No | O98: 0 | P98: 450 | Q98: In Stock
A99: BLOOM CUTICURA TALC POWDER 100GM | C99: Healthcare Items | D99: 8904018300348 | F99: 0 | G99: 105 | H99: Exclusive | I99: 102 | J99: Exclusive | K99: 105 | L99: 0 | M99: 1 | N99: Yes | O99: 0 | P99: 450 | Q99: In Stock
A100: BOOK BENNY HYNN | C100: Books & Bibles | D100: 100041 | F100: 0 | G100: 150 | H100: Inclusive | I100: 140 | J100: Inclusive | K100: 200 | L100: 0 | M100: 1 | N100: Yes | O100: 0 | P100: 450 | Q100: In Stock
A101: BOOK BETTER EVERY DAY MALAYALAM | C101: Books & Bibles | D101: 485750742271 | F101: 0 | G101: 200 | H101: Inclusive | I101: 180 | J101: Inclusive | K101: 250 | L101: 0 | M101: 1 | N101: Yes | O101: 0 | P101: 450 | Q101: In Stock
A102: BOOK - DESPITE TO HOPE | C102: Books & Bibles | D102: 100042 | F102: 0 | G102: 50 | H102: Inclusive | I102: 31.5 | J102: Inclusive | K102: 60 | L102: 1 | M102: 1 | N102: Yes | O102: 0 | P102: 450 | Q102: In Stock
A103: BOOK GAVAHON KA BAADAL 1 | C103: Books & Bibles | D103: 100043 | F103: 0 | G103: 150 | H103: Inclusive | I103: 140 | J103: Inclusive | K103: 200 | L103: 0 | M103: 1 | N103: Yes | O103: 0 | P103: 450 | Q103: In Stock
... A136: BV BANANA POWDER 300GM | C136: Grains & Flours | D136: 8906009162447 | F136: 0 | G136: 295 | H136: Exclusive | I136: 258 | J136: Exclusive | K136: 295 | L136: 2 | M136: 1 | N136: Yes | O136: 0 | P136: 450 | Q136: In Stock
A137: CABBAGE THORAN | C137: Ready to Eat & Mixes | D137: 8907093007690 | F137: 0 | G137: 150 | H137: Exclusive | I137: 120 | J137: Exclusive | K137: 150 | L137: 0 | N137: Yes | O137: 0 | P137: 450 | Q137: In Stock
A138: CALENDAR 2026 | C138: Stationery | D138: 100073 | F138: 0 | G138: 50 | H138: Exclusive | I138: 27 | J138: Exclusive | K138: 50 | L138: 313 | M138: 1 | N138: Yes | O138: 0 | P138: 450 | Q138: In Stock
A139: CARDAMOM POWDER 50GM | C139: Masalas & Spices | D139: 707455637792 | F139: 0 | G139: 199 | H139: Inclusive | I139: 150 | J139: Inclusive | K139: 249 | L139: 2 | M139: 1 | N139: Yes | O139: 0 | P139: 450 | Q139: In Stock
A140: CARDBOARD | C140: Stationery | D140: 100074 | F140: 0 | G140: 80 | H140: Exclusive | I140: 40 | J140: Exclusive | K140: 80 | L140: 0 | M140: 1 | N140: No | O140: 0 | P140: 450 | Q140: In Stock
A141: CATCH CORIANDER 1KG | C141: Masalas & Spices | D141: 8901192104724 | F141: 0 | G141: 360 | H141: Exclusive | I141: 304 | J141: Exclusive | K141: 390 | L141: 1 | M141: 1 | N141: Yes | O141: 0 | P141: 450 | Q141: In Stock
A142: CATCH CORIANDER 250GM | C142: Masalas & Spices | D142: 8901192104229 | F142: 0 | G142: 79 | H142: Exclusive | I142: 66 | J142: Exclusive | K142: 82 | L142: 0 | M142: 1 | N142: Yes | O142: 0 | P142: 450 | Q142: In Stock
A143: CELO TAPE | C143: Stationery | D143: 100075 | F143: 0 | G143: 12 | H143: Exclusive | I143: 10 | J143: Exclusive | K143: 12 | L143: 15 | M143: 1 | N143: No | O143: 0 | P143: 450 | Q143: In Stock
A144: CHANDRIKA AYURVEDIC SOAP 75GM | C144: Healthcare Items | D144: 8901399009020 | F144: 0 | G144: 32 | H144: Exclusive | I144: 33 | J144: Exclusive | K144: 33 | L144: 0 | M144: 1 | N144: Yes | O144: 0 | P144: 450 | Q144: In Stock
A145: CHANDRIKA SOAP3+1 | C145: Healthcare Items | D145: 8901399006920 | F145: 0 | G145: 165 | H145: Exclusive | I145: 160 | J145: Exclusive | K145: 165 | L145: 0 | M145: 1 | N145: Yes | O145: 0 | P145: 450 | Q145: In Stock
A146: CHART PAPER 10 | C146: Stationery | D146: 100076 | F146: 0 | G146: 10 | H146: Exclusive | I146: 3 | J146: Exclusive | K146: 10 | L146: 48 | M146: 1 | N146: No | O146: 0 | P146: 450 | Q146: In Stock
A147: CHENNAI STAR BLACK VELLAM KARUPPETTI 500GM | C147: Ready to Eat & Mixes | D147: 316859855751 | F147: 0 | G147: 250 | H147: Exclusive | I147: 210 | J147: Exclusive | K147: 250 | L147: 0 | M147: 1 | N147: Yes | O147: 0 | P147: 450 | Q147: In Stock
A148: CHERU PAZHAM NJALI (SMALL BANANA) | C148: Raw Items & Produce | D148: 923495130917 | F148: 0 | G148: 150 | H148: Exclusive | I148: 80 | J148: Exclusive | K148: 140 | L148: 0 | M148: 1 | N148: Yes | O148: 0 | P148: 450 | Q148: In Stock
A149: CHIA SEEDS 250GM | C149: Snacks | D149: 100077 | F149: 0 | G149: 190 | H149: Inclusive | I149: 153 | J149: Inclusive | K149: 190 | L149: 0 | M149: 1 | N149: Yes | O149: 0 | P149: 450 | Q149: In Stock
... A157: CHOICE BANANA CHIPS 1KG | C157: Snacks | D157: 190036369719 | F157: 0 | G157: 520 | H157: Exclusive | I157: 245 | J157: Exclusive | K157: 500 | L157: 0 | M157: 1 | N157: Yes | O157: 0 | P157: 450 | Q157: In Stock
A158: CHOICE BANANA CHIPS 200GM PALM OIL | C158: Snacks | D158: 100083 | F158: 0 | G158: 80 | H158: Exclusive | I158: 68 | J158: Exclusive | K158: 80 | L158: 25 | N158: Yes | O158: 0 | P158: 450 | Q158: In Stock
A159: CHOICE BANANA CHIPS 500GM | C159: Snacks | D159: 648750284351 | F159: 0 | G159: 375 | H159: Exclusive | I159: 170 | J159: Exclusive | K159: 350 | L159: 30 | M159: 1 | N159: Yes | O159: 0 | P159: 450 | Q159: In Stock
A160: CHOICE BANANA CHIPS COCONUT OIL 200GM | C160: Snacks | D160: 100084 | F160: 0 | G160: 120 | H160: Inclusive | I160: 90 | J160: Inclusive | K160: 120 | L160: 60 | N160: No | O160: 0 | P160: 450 | Q160: In Stock
A161: CHOICE BANANA CHIPS PALMOIL 200GM | C161: Snacks | D161: 8939116617876 | F161: 0 | G161: 100 | H161: Exclusive | I161: 110 | J161: Exclusive | K161: 150 | L161: 0 | M161: 1 | N161: Yes | O161: 0 | P161: 450 | Q161: In Stock
A162: CHOICE JACKFRUIT CHIPS 200GM | C162: Snacks | D162: 100085 | F162: 0 | G162: 124 | H162: Exclusive | I162: 100 | J162: Exclusive | K162: 140 | L162: 13 | M162: 1 | N162: Yes | O162: 0 | P162: 450 | Q162: In Stock
A163: CHOICE KERALA MIXTURE 250GM | C163: Snacks | D163: 8902345823004 | F163: 0 | G163: 100 | H163: Exclusive | I163: 75 | J163: Exclusive | K163: 100 | L163: 0 | M163: 1 | N163: Yes | O163: 0 | P163: 450 | Q163: In Stock
A164: CHOICE SARKKARA UPPERI 250GM | C164: Snacks | D164: 100086 | F164: 0 | G164: 100 | H164: Exclusive | I164: 60.95 | J164: Exclusive | K164: 0 | L164: 0 | N164: Yes | O164: 0 | P164: 450 | Q164: In Stock
A165: CHOICE SHARKARA VARATTI UPPERI | C165: Snacks | D165: 915104510674 | F165: 0 | G165: 100 | H165: Exclusive | I165: 80 | J165: Exclusive | K165: 125 | L165: 0 | M165: 1 | N165: Yes | O165: 0 | P165: 450 | Q165: In Stock
A166: CHOICE SHARKARA VARATTI UPPERI 500GM | C166: Snacks | D166: 648844689464 | F166: 0 | G166: 250 | H166: Exclusive | I166: 154 | J166: Exclusive | K166: 250 | L166: 0 | M166: 1 | N166: Yes | O166: 0 | P166: 450 | Q166: In Stock
A167: CHOORAL STICKS (BETH) | C167: Household & Cleaning | D167: 100088 | F167: 0 | G167: 30 | H167: Exclusive | I167: 10 | J167: Exclusive | K167: 35 | L167: 7 | M167: 1 | N167: Yes | O167: 0 | P167: 450 | Q167: In Stock
A168: CHRISTIAN TIE | C168: Kerala Clothing | D168: 100089 | F168: 0 | G168: 280 | H168: Inclusive | I168: 200 | J168: Inclusive | K168: 300 | L168: 0 | M168: 1 | N168: Yes | O168: 0 | P168: 450 | Q168: In Stock
A169: CHRISTMAS CAKE 250GM | C169: Snacks | D169: 235014986981 | F169: 0 | G169: 245 | H169: Exclusive | I169: 220 | J169: Exclusive | K169: 250 | L169: 0 | M169: 1 | N169: Yes | O169: 0 | P169: 450 | Q169: In Stock
...

Sheet Sales_Invoicing
A1: Invoice No. | B1: Date | C1: Customer Name | D1: Item Name | E1: HSN Code | F1: Quantity | G1: Rate (₹) | H1: Taxable Value (₹) | I1: GST Rate (%) | J1: CGST (₹) | K1: SGST (₹) | L1: Total Amount (₹) | M1: Payment Status | N1: Payment Mode / Notes | O1: Unit Cost (₹) | P1: COGS (₹) | Q1: Gross Profit (₹)
A2: INV-20261004-234534 | B2: 46299.99 | C2: John Joy Raj | D2: KERALA BANANA | F2: 1.5 | G2: 135 | H2: 202.5 | I2: 0 | J2: 0 | K2: 0 | L2: 202.5 | M2: Paid | N2: Bank | O2: {=IF(D2="","", IFERROR(_xlfn.XLOOKUP(D2, Inventory_Master!A:A, Inventory_Master!I:I, 0), 0))} | P2: =IF(O2="","", F2 * O2) | Q2: =IF(L2="","", L2 - P2)
A3: INV-20261004-234534 | B3: 46299.99 | C3: John Joy Raj | D3: IDAYAM NALLENNA BOTTLE 500GM | F3: 1 | G3: 243 | H3: 243 | I3: 0 | J3: 0 | K3: 0 | L3: 243 | M3: Paid | N3: Bank | O3: {=IF(D3="","", IFERROR(_xlfn.XLOOKUP(D3, Inventory_Master!A:A, Inventory_Master!I:I, 0), 0))} | P3: =IF(O3="","", F3 * O3) | Q3: =IF(L3="","", L3 - P3)
A4: INV-20261004-234534 | B4: 46299.99 | C4: John Joy Raj | D4: KAPPA TAPIOCA | F4: 5.3 | G4: 90 | H4: 477 | I4: 0 | J4: 0 | K4: 0 | L4: 477 | M4: Paid | N4: Bank | O4: {=IF(D4="","", IFERROR(_xlfn.XLOOKUP(D4, Inventory_Master!A:A, Inventory_Master!I:I, 0), 0))} | P4: =IF(O4="","", F4 * O4) | Q4: =IF(L4="","", L4 - P4)
A5: INV-20261005-000442 | B5: 46300.003 | C5: joy | D5: HOL CHEELU KAPPA CHIPS | F5: 1 | G5: 92 | H5: 92 | I5: 0 | J5: 0 | K5: 0 | L5: 92 | M5: Paid | N5: Bank | O5: {=IF(D5="","", IFERROR(_xlfn.XLOOKUP(D5, Inventory_Master!A:A, Inventory_Master!I:I, 0), 0))} | P5: =IF(O5="","", F5 * O5) | Q5: =IF(L5="","", L5 - P5)
A6: INV-20261005-001225 | B6: 46300.009 | C6: Joy | D6: KAPPA TAPIOCA | F6: 1.5 | G6: 90 | H6: 135 | I6: 0 | J6: 0 | K6: 0 | L6: 135 | M6: Paid | N6: Bank | O6: {=IF(D6="","", IFERROR(_xlfn.XLOOKUP(D6, Inventory_Master!A:A, Inventory_Master!I:I, 0), 0))} | P6: =IF(O6="","", F6 * O6) | Q6: =IF(L6="","", L6 - P6)
A7: INV-20261005-001225 | B7: 46300.009 | C7: Joy | D7: KPL COCONUT OIL 500GM | F7: 1 | G7: 365 | H7: 365 | I7: 0 | J7: 0 | K7: 0 | L7: 365 | M7: Paid | N7: Bank | O7: {=IF(D7="","", IFERROR(_xlfn.XLOOKUP(D7, Inventory_Master!A:A, Inventory_Master!I:I, 0), 0))} | P7: =IF(O7="","", F7 * O7) | Q7: =IF(L7="","", L7 - P7)
A8: INV-20261005-004102 | B8: 46300.028 | C8: Suja | D8: KAPPA TAPIOCA | F8: 1.5 | G8: 90 | H8: 135 | I8: 0 | J8: 0 | K8: 0 | L8: 135 | M8: Paid | N8: Bank | O8: {=IF(D8="","", IFERROR(_xlfn.XLOOKUP(D8, Inventory_Master!A:A, Inventory_Master!I:I, 0), 0))} | P8: =IF(O8="","", F8 * O8) | Q8: =IF(L8="","", L8 - P8)
A9: INV-20261005-004102 | B9: 46300.028 | C9: Suja | D9: KERALA BANANA | F9: 3.5 | G9: 135 | H9: 472.5 | I9: 0 | J9: 0 | K9: 0 | L9: 472.5 | M9: Paid | N9: Bank | O9: {=IF(D9="","", IFERROR(_xlfn.XLOOKUP(D9, Inventory_Master!A:A, Inventory_Master!I:I, 0), 0))} | P9: =IF(O9="","", F9 * O9) | Q9: =IF(L9="","", L9 - P9)
A10: INV-20261005-100357 | B10: 46300.419 | C10: Joy Raj | D10: COOKED RICE | F10: 1 | G10: 80 | H10: 80 | I10: 0 | J10: 0 | K10: 0 | L10: 80 | M10: Paid | N10: Bank | O10: {=IF(D10="","", IFERROR(_xlfn.XLOOKUP(D10, Inventory_Master!A:A, Inventory_Master!I:I, 0), 0))} | P10: =IF(O10="","", F10 * O10) | Q10: =IF(L10="","", L10 - P10)
A11: INV-20261005-100357 | B11: 46300.419 | C11: Joy Raj | D11: KALAN | F11: 1 | G11: 150 | H11: 150 | I11: 0 | J11: 0 | K11: 0 | L11: 150 | M11: Paid | N11: Bank | O11: {=IF(D11="","", IFERROR(_xlfn.XLOOKUP(D11, Inventory_Master!A:A, Inventory_Master!I:I, 0), 0))} | P11: =IF(O11="","", F11 * O11) | Q11: =IF(L11="","", L11 - P11)
A12: INV-20261005-100357 | B12: 46300.419 | C12: Joy Raj | D12: TN SAMBAR RTE | F12: 1 | G12: 140 | H12: 140 | I12: 0 | J12: 0 | K12: 0 | L12: 140 | M12: Paid | N12: Bank | O12: {=IF(D12="","", IFERROR(_xlfn.XLOOKUP(D12, Inventory_Master!A:A, Inventory_Master!I:I, 0), 0))} | P12: =IF(O12="","", F12 * O12) | Q12: =IF(L12="","", L12 - P12)
A13: INV-20261005-105131 | B13: 46300.452 | C13: joy ktl | D13: KAPPA TAPIOCA | F13: 3 | G13: 90 | H13: 270 | I13: 0 | J13: 0 | K13: 0 | L13: 270 | M13: Paid | N13: Bank
A14: INV-20261005-105131 | B14: 46300.452 | C14: joy ktl | D14: KERALA BANANA | F14: 1 | G14: 135 | H14: 135 | I14: 0 | J14: 0 | K14: 0 | L14: 135 | M14: Paid | N14: Bank
A15: INV-20261005-105131 | B15: 46300.452 | C15: joy ktl | D15: SMALL ONION ULLI | F15: 1 | G15: 145 | H15: 145 | I15: 0 | J15: 0 | K15: 0 | L15: 145 | M15: Paid | N15: Bank
A16: INV-20261005-114137 | B16: 46300.487 | C16: Suja | D16: CHOICE KERALA MIXTURE 250GM | F16: 1 | G16: 100 | H16: 100 | I16: 0 | J16: 0 | K16: 0 | L16: 100 | M16: Paid | N16: Bank
A17: INV-20261005-114137 | B17: 46300.487 | C17: Suja | D17: KUTTAN'S PAYYOLI MIXTURE 500GM | F17: 1 | G17: 150 | H17: 150 | I17: 0 | J17: 0 | K17: 0 | L17: 150 | M17: Paid | N17: Bank
A18: INV-20261005-114137 | B18: 46300.487 | C18: Suja | D18: HOL VETTU CAKE 6PC | F18: 1 | G18: 75 | H18: 75 | I18: 0 | J18: 0 | K18: 0 | L18: 75 | M18: Paid | N18: Bank
A19: INV-20261005-114137 | B19: 46300.487 | C19: Suja | D19: ELITE BANANA PUDDING 250 | F19: 1 | G19: 150 | H19: 150 | I19: 0 | J19: 0 | K19: 0 | L19: 150 | M19: Paid | N19: Bank
A101: INV-TEST-202610100946 | B101: 46305.408 | C101: Test Customer (Gorakhpur) | D101: 120W TYPE C CABLE | F101: 1 | G101: 60 | H101: 60 | I101: 0 | J101: 0 | K101: 0 | L101: 60

Sheet Purchases_Vendors
A1: Bill / PO No. | B1: Bill Date | C1: Vendor Name | D1: Item / Service Description | E1: HSN / SAC | F1: Quantity | G1: Unit Purchase Price (₹) | H1: Taxable Value (₹) | I1: GST Rate (%) | J1: Total Bill Amount (₹) | K1: Payment Status | L1: Input Tax Credit (ITC)
H7: =IF(ISBLANK(F7), "", F7*G7) | J7: =IF(OR(ISBLANK(H7), H7=""), "", H7*(1+N(I7)))
H8: =IF(ISBLANK(F8), "", F8*G8) | J8: =IF(OR(ISBLANK(H8), H8=""), "", H8*(1+N(I8)))
H9: =IF(ISBLANK(F9), "", F9*G9) | J9: =IF(OR(ISBLANK(H9), H9=""), "", H9*(1+N(I9)))
H10: =IF(ISBLANK(F10), "", F10*G10) | J10: =IF(OR(ISBLANK(H10), H10=""), "", H10*(1+N(I10)))
H11: =IF(ISBLANK(F11), "", F11*G11) | J11: =IF(OR(ISBLANK(H11), H11=""), "", H11*(1+N(I11)))
H12: =IF(ISBLANK(F12), "", F12*G12) | J12: =IF(OR(ISBLANK(H12), H12=""), "", H12*(1+N(I12)))
H13: =IF(ISBLANK(F13), "", F13*G13) | J13: =IF(OR(ISBLANK(H13), H13=""), "", H13*(1+N(I13)))
H14: =IF(ISBLANK(F14), "", F14*G14) | J14: =IF(OR(ISBLANK(H14), H14=""), "", H14*(1+N(I14)))
H15: =IF(ISBLANK(F15), "", F15*G15) | J15: =IF(OR(ISBLANK(H15), H15=""), "", H15*(1+N(I15)))
H16: =IF(ISBLANK(F16), "", F16*G16) | J16: =IF(OR(ISBLANK(H16), H16=""), "", H16*(1+N(I16)))
H17: =IF(ISBLANK(F17), "", F17*G17) | J17: =IF(OR(ISBLANK(H17), H17=""), "", H17*(1+N(I17)))
H18: =IF(ISBLANK(F18), "", F18*G18) | J18: =IF(OR(ISBLANK(H18), H18=""), "", H18*(1+N(I18)))
... H100: =IF(ISBLANK(F100), "", F100*G100) | J100: =IF(OR(ISBLANK(H100), H100=""), "", H100*(1+N(I100)))

Sheet Parties_Directory
A1: NAME | B1: MOBILE | C1: MODE | D1: BALANCE
A2: Akshay Verma | B2: 4477233719 | C2: Customer | D2: ₹ 0
A3: Wilson Uncle25 | B3: 4712245785 | C3: Customer | D3: ₹ 0
A4: Little flower chargawa Lfs gorakhpur | B4: 5512504941 | C4: Customer | D4: ₹ 0
A5: Joel | B5: 6001922077 | C5: Customer | D5: ₹ 0
A6: Bleson | B6: 6203349657 | C6: Customer | D6: ₹ 0
A7: Mrs.Martin | B7: 6206150511 | C7: Customer | D7: ₹ 0
A8: Ashok | B8: 6206464368 | C8: Customer | D8: ₹ 0
A9: Mini | B9: 6235466149 | C9: Customer | D9: ₹ 0
A10: Joncy Teacher GMS | B10: 6235891472 | C10: Customer | D10: ₹ 0
A11: Vinu | B11: 6238226270 | C11: Customer | D11: ₹ 0
A12: Akash Dharampur | B12: 6238234689 | C12: Customer | D12: ₹ 0
A13: Rakesh | B13: 6238391310 | C13: Customer | D13: ₹ 0
... A18: Msmi Convent Gida | B18: 6267555369 | C18: Customer | D18: ₹ 0
A19: Adithya | C19: Customer | D19: ₹ 0
A20: Viju Abraham | B20: 6282158418 | C20: Customer | D20: ₹ 0
A21: Tojus | B21: 6282268412 | C21: Customer | D21: ₹ 0
A22: Jomish | B22: 6282498587 | C22: Customer | D22: ₹ 0
A23: Shanto Mon | B23: 6282547683 | C23: Customer | D23: ₹ 0
A24: Unni | B24: 6282764891 | C24: Customer | D24: ₹ 0
A25: Shibin | B25: 6282849475 | C25: Customer | D25: ₹ 0
A26: Dr.Raj | B26: 6302851076 | C26: Customer | D26: ₹ 0
A27: John | B27: 6303998605 | C27: Customer | D27: ₹ 0
A28: Sajin | B28: 6306091395 | C28: Customer | D28: ₹ 0
A29: Naveen | B29: 6306093002 | C29: Customer | D29: ₹ 0
A30: Harry Joshua | B30: 6306202868 | C30: Customer | D30: ₹ 0
A31: Jophin | B31: 6306225015 | C31: Customer | D31: ₹ 0
... A1192: Anubhav Sharma | B1192: 9838839349 | C1192: Customer | D1192: ₹ 0
A1193: A.K Vishwash | B1193: 9838925325 | C1193: Customer | D1193: ₹ 0 | E1193: =MATCH("Anna Cafe Maharajganj", A:A, 0)
A1194: Kanhaya Lal Gupta | B1194: 9838948813 | C1194: Customer | D1194: ₹ 0
A1195: Nasiruddin | B1195: 9839100359 | C1195: Customer | D1195: ₹ 0
A1196: Williamhazkeal | B1196: 9839173043 | C1196: Customer | D1196: ₹ 0
A1197: Robin | B1197: 9839245783 | C1197: Customer | D1197: ₹ 0
A1198: Pr. Ani George Nanda Nagar | B1198: 9839280922 | C1198: Customer | D1198: ₹ 0
A1199: Lst Convent Khorabar | B1199: 9839693949 | C1199: Customer | D1199: ₹ 0
A1200: Narendra Tirpathi | B1200: 9839777784 | C1200: Customer | D1200: ₹ 0
A1201: Depali | B1201: 9839937388 | C1201: Customer | D1201: ₹ 0
A1202: Nargis | B1202: 9839946515 | C1202: Customer | D1202: ₹ 0
A1203: Dilip Malayali | B1203: 9843399222 | C1203: Customer | D1203: ₹ 0
A1204: Afeel | B1204: 9846587947 | C1204: Customer | D1204: ₹ 0
A1205: Ratish | B1205: 9846628675 | C1205: Customer | D1205: ₹ 0
... A1332: Mamta | B1332: 9997603706 | C1332: Customer | D1332: ₹ 0
A1333: joy ktl | C1333: Customer | D1333: 0

Sheet Pending_Payments
B1: 💳 SHALOM • PENDING PAYMENTS & ACCOUNTS RECEIVABLE MANAGEMENT
B3: TOTAL RECEIVABLE DUES | D3: UNPAID SALES INVOICES | F3: DIRECTORY CUSTOMER DUES | H3: OVERDUE DUES (>30 DAYS) | J3: FOLLOW-UP READINESS
B4: =H16 | D4: =COUNTIF(F8:F100, "Sales Invoice") | F4: =COUNTIF(F8:F100, "Directory Ledger") | H4: =COUNTIF(J8:J100, "*Overdue*") | J4: 100% READY
B5: All unpaid invoices & ledger balances | D5: =TEXT(SUMIF(F8:F100, "Sales Invoice", H8:H100), "₹#,##0.00") & " from Invoicing" | F5: =TEXT(SUMIF(F8:F100, "Directory Ledger", H8:H100), "₹#,##0.00") & " Ledger Dues" | H5: Priority collections required | J5: Direct WhatsApp Action Links
B7: Invoice / Ref # | C7: Date | D7: Customer / Party Name | E7: Mobile Number | F7: Source Type | G7: Payment Status | H7: Pending Amount (₹) | I7: Days Overdue | J7: Aging Tier | K7: 1-Click WhatsApp Reminder
B8: INV-20261005-000442 | C8: 46300 | D8: joy | E8: {=IFERROR(_xlfn.XLOOKUP(D8, Parties_Directory!A$2:A100, Parties_Directory!B$2:B100, _xlfn.XLOOKUP("*"&D8&"*", Parties_Directory!A$2:A100, Parties_Directory!B$2:B100, "Not Available", 2)), "Not Available")} | F8: Sales Invoice | G8: Unpaid | H8: =SUMIFS(Sales_Invoicing!L:L, Sales_Invoicing!A:A, B8, Sales_Invoicing!M:M, "Unpaid") | I8: =IFERROR(__xludf.DUMMYFUNCTION("IF(C8="""", """", MAX(0, TODAY() - DATEVALUE(TO_TEXT(C8))))"),5) | J8: =IF(I8="", "", IF(I8<=15, "Current (0-15 Days)", IF(I8<=30, "Due (16-30 Days)", "Overdue (>30 Days)"))) | K8: =IFERROR(__xludf.DUMMYFUNCTION("IF(AND(E8<>""Not Available"", E8<>""""), HYPERLINK(""https://wa.me/91"" & REGEXREPLACE(TO_TEXT(E8), ""[^0-9]"", """") & ""?text="" & ENCODEURL(""Hello "" & D8 & "", this is a friendly reminder from SHALOM regarding your pending balance of ₹"" & TEXT(H8, "&"""#,##0.00"") & "" (Ref: "" & B8 & ""). Kindly arrange the payment at your earliest convenience. Thank you!""), ""💬 Send WhatsApp Reminder""), ""— (No Contact)"")"),"💬 Send WhatsApp Reminder")
B9: INV-20261005-004102 | C9: 46300 | D9: Suja | E9: {=IFERROR(_xlfn.XLOOKUP(D9, Parties_Directory!A$2:A100, Parties_Directory!B$2:B100, _xlfn.XLOOKUP("*"&D9&"*", Parties_Directory!A$2:A100, Parties_Directory!B$2:B100, "Not Available", 2)), "Not Available")} | F9: Sales Invoice | G9: Unpaid | H9: =SUMIFS(Sales_Invoicing!L:L, Sales_Invoicing!A:A, B9, Sales_Invoicing!M:M, "Unpaid") | I9: =IFERROR(__xludf.DUMMYFUNCTION("IF(C9="""", """", MAX(0, TODAY() - DATEVALUE(TO_TEXT(C9))))"),5) | J9: =IF(I9="", "", IF(I9<=15, "Current (0-15 Days)", IF(I9<=30, "Due (16-30 Days)", "Overdue (>30 Days)"))) | K9: =IFERROR(__xludf.DUMMYFUNCTION("IF(AND(E9<>""Not Available"", E9<>""""), HYPERLINK(""https://wa.me/91"" & REGEXREPLACE(TO_TEXT(E9), ""[^0-9]"", """") & ""?text="" & ENCODEURL(""Hello "" & D8 & "", this is a friendly reminder from SHALOM regarding your pending balance of ₹"" & TEXT(H9, "&"""#,##0.00"") & "" (Ref: "" & B9 & ""). Kindly arrange the payment at your earliest convenience. Thank you!""), ""💬 Send WhatsApp Reminder""), ""— (No Contact)"")"),"— (No Contact)")
B10: DIR-LEDGER-01 | C10: 46280 | D10: Akhilesh Malayalee Air Force Gkp | E10: {=IFERROR(_xlfn.XLOOKUP(D10, Parties_Directory!A$2:A100, Parties_Directory!B$2:B100, "Not Available"), "Not Available")} | F10: Directory Ledger | G10: Overdue | H10: 58935.32 | I10: =IFERROR(__xludf.DUMMYFUNCTION("IF(C10="""", """", MAX(0, TODAY() - DATEVALUE(TO_TEXT(C10))))"),25) | J10: =IF(I10="", "", IF(I10<=15, "Current (0-15 Days)", IF(I10<=30, "Due (16-30 Days)", "Overdue (>30 Days)"))) | K10: =IFERROR(__xludf.DUMMYFUNCTION("IF(AND(E10<>""Not Available"", E10<>""""), HYPERLINK(""https://wa.me/91"" & REGEXREPLACE(TO_TEXT(E10), ""[^0-9]"", """") & ""?text="" & ENCODEURL(""Hello "" & D10 & "", this is a friendly reminder from SHALOM STORES regarding your pending balance of ₹"" &"&" TEXT(H10, ""#,##0.00"") & "" (Ref: "" & B10 & ""). Kindly arrange the payment at your earliest convenience. Thank you!""), ""💬 Send WhatsApp Reminder""), ""— (No Contact)"")"),"💬 Send WhatsApp Reminder")
B11: DIR-LEDGER-02 | C11: 46285 | D11: Reeba Chechi 2022 | E11: {=IFERROR(_xlfn.XLOOKUP(D11, Parties_Directory!A$2:A100, Parties_Directory!B$2:B100, "Not Available"), "Not Available")} | F11: Directory Ledger | G11: Overdue | H11: 24746.8 | I11: =IFERROR(__xludf.DUMMYFUNCTION("IF(C11="""", """", MAX(0, TODAY() - DATEVALUE(TO_TEXT(C11))))"),20) | J11: =IF(I11="", "", IF(I11<=15, "Current (0-15 Days)", IF(I11<=30, "Due (16-30 Days)", "Overdue (>30 Days)"))) | K11: =IFERROR(__xludf.DUMMYFUNCTION("IF(AND(E11<>""Not Available"", E11<>""""), HYPERLINK(""https://wa.me/91"" & REGEXREPLACE(TO_TEXT(E11), ""[^0-9]"", """") & ""?text="" & ENCODEURL(""Hello "" & D11 & "", this is a friendly reminder from SHALOM regarding your pending balance of ₹"" & TEXT(H"&"11, ""#,##0.00"") & "" (Ref: "" & B11 & ""). Kindly arrange the payment at your earliest convenience. Thank you!""), ""💬 Send WhatsApp Reminder""), ""— (No Contact)"")"),"💬 Send WhatsApp Reminder")
B12: DIR-LEDGER-03 | C12: 46290 | D12: Shambhoo Chouhan | E12: {=IFERROR(_xlfn.XLOOKUP(D12, Parties_Directory!A$2:A100, Parties_Directory!B$2:B100, "Not Available"), "Not Available")} | F12: Directory Ledger | G12: Overdue | H12: 12653 | I12: =IFERROR(__xludf.DUMMYFUNCTION("IF(C12="""", """", MAX(0, TODAY() - DATEVALUE(TO_TEXT(C12))))"),15) | J12: =IF(I12="", "", IF(I12<=15, "Current (0-15 Days)", IF(I12<=30, "Due (16-30 Days)", "Overdue (>30 Days)"))) | K12: =IFERROR(__xludf.DUMMYFUNCTION("IF(AND(E12<>""Not Available"", E12<>""""), HYPERLINK(""https://wa.me/91"" & REGEXREPLACE(TO_TEXT(E12), ""[^0-9]"", """") & ""?text="" & ENCODEURL(""Hello "" & D12 & "", this is a friendly reminder from SHALOM regarding your pending balance of ₹"" & TEXT(H"&"12, ""#,##0.00"") & "" (Ref: "" & B12 & ""). Kindly arrange the payment at your earliest convenience. Thank you!""), ""💬 Send WhatsApp Reminder""), ""— (No Contact)"")"),"💬 Send WhatsApp Reminder")
B13: DIR-LEDGER-04 | C13: 46293 | D13: Anna Cafe Maharajganj | E13: {=IFERROR(_xlfn.XLOOKUP(D13, Parties_Directory!A$2:A100, Parties_Directory!B$2:B100, "Not Available"), "Not Available")} | F13: Directory Ledger | G13: Overdue | H13: 9276.05 | I13: =IFERROR(__xludf.DUMMYFUNCTION("IF(C13="""", """", MAX(0, TODAY() - DATEVALUE(TO_TEXT(C13))))"),12) | J13: =IF(I13="", "", IF(I13<=15, "Current (0-15 Days)", IF(I13<=30, "Due (16-30 Days)", "Overdue (>30 Days)"))) | K13: =IFERROR(__xludf.DUMMYFUNCTION("IF(AND(E13<>""Not Available"", E13<>""""), HYPERLINK(""https://wa.me/91"" & REGEXREPLACE(TO_TEXT(E13), ""[^0-9]"", """") & ""?text="" & ENCODEURL(""Hello "" & D13 & "", this is a friendly reminder from SHALOM regarding your pending balance of ₹"" & TEXT(H"&"13, ""#,##0.00"") & "" (Ref: "" & B13 & ""). Kindly arrange the payment at your earliest convenience. Thank you!""), ""💬 Send WhatsApp Reminder""), ""— (No Contact)"")"),"💬 Send WhatsApp Reminder")
B14: DIR-LEDGER-05 | C14: 46296 | D14: Daniel LEF GKP | E14: {=IFERROR(_xlfn.XLOOKUP(D14, Parties_Directory!A$2:A100, Parties_Directory!B$2:B100, "Not Available"), "Not Available")} | F14: Directory Ledger | G14: Due | H14: 7000 | I14: =IFERROR(__xludf.DUMMYFUNCTION("IF(C14="""", """", MAX(0, TODAY() - DATEVALUE(TO_TEXT(C14))))"),9) | J14: =IF(I14="", "", IF(I14<=15, "Current (0-15 Days)", IF(I14<=30, "Due (16-30 Days)", "Overdue (>30 Days)"))) | K14: =IFERROR(__xludf.DUMMYFUNCTION("IF(AND(E14<>""Not Available"", E14<>""""), HYPERLINK(""https://wa.me/91"" & REGEXREPLACE(TO_TEXT(E14), ""[^0-9]"", """") & ""?text="" & ENCODEURL(""Hello "" & D14 & "", this is a friendly reminder from SHALOM regarding your pending balance of ₹"" & TEXT(H"&"14, ""#,##0.00"") & "" (Ref: "" & B14 & ""). Kindly arrange the payment at your earliest convenience. Thank you!""), ""💬 Send WhatsApp Reminder""), ""— (No Contact)"")"),"💬 Send WhatsApp Reminder")
B15: DIR-LEDGER-06 | C15: 46297 | D15: Aneesh | E15: {=IFERROR(_xlfn.XLOOKUP(D15, Parties_Directory!A$2:A100, Parties_Directory!B$2:B100, "Not Available"), "Not Available")} | F15: Directory Ledger | G15: Due | H15: 1189 | I15: =IFERROR(__xludf.DUMMYFUNCTION("IF(C15="""", """", MAX(0, TODAY() - DATEVALUE(TO_TEXT(C15))))"),8) | J15: =IF(I15="", "", IF(I15<=15, "Current (0-15 Days)", IF(I15<=30, "Due (16-30 Days)", "Overdue (>30 Days)"))) | K15: =IFERROR(__xludf.DUMMYFUNCTION("IF(AND(E15<>""Not Available"", E15<>""""), HYPERLINK(""https://wa.me/91"" & REGEXREPLACE(TO_TEXT(E15), ""[^0-9]"", """") & ""?text="" & ENCODEURL(""Hello "" & D15 & "", this is a friendly reminder from SHALOM regarding your pending balance of ₹"" & TEXT(H"&"15, ""#,##0.00"") & "" (Ref: "" & B15 & ""). Kindly arrange the payment at your earliest convenience. Thank you!""), ""💬 Send WhatsApp Reminder""), ""— (No Contact)"")"),"💬 Send WhatsApp Reminder")
B16: TOTAL OUTSTANDING | H16: =SUM(H8:H15)

Sheet Analytics_Dashboard
B2: 📊 EXECUTIVE SALES & PROFIT ANALYTICS | H2: 🧾 BILL PAGE | J2: ✏️ EDIT PAGE | L2: 🛒 PURCHASE PAGE | N2: 🏠 DASHBOARD
B5: ⏳ Select Reporting Timeframe: | D5: Monthly | F5: ="Showing: " & D5 & " Performance"
B7: 📦 TOTAL STOCK VALUE | F7: ="💰 TOTAL SALES (" & UPPER(D5) & ")" | J7: ="📈 GROSS PROFIT (" & UPPER(D5) & ")" | M7: ="🎯 PROFIT MARGIN (" & UPPER(D5) & ")"
B8: =SUM(Inventory_Master!P2:P100) | F8: =_xludf.IFS(D5="Daily", SUMIFS(Sales_Invoicing!L:L, Sales_Invoicing!B:B, ">="&TODAY(), Sales_Invoicing!B:B, "<"&TODAY()+1), D5="Monthly", SUMIFS(Sales_Invoicing!L:L, Sales_Invoicing!B:B, ">="&DATE(YEAR(TODAY()), MONTH(TODAY()), 1), Sales_Invoicing!B:B, "<"&EDATE(DATE(YEAR(TODAY()), MONTH(TODAY()), 1), 1)), D5="Quarterly", SUMIFS(Sales_Invoicing!L:L, Sales_Invoicing!B:B, ">="&DATE(YEAR(TODAY()), INT((MONTH(TODAY())-1)/3)*3+1, 1), Sales_Invoicing!B:B, "<"&EDATE(DATE(YEAR(TODAY()), INT((MONTH(TODAY())-1)/3)*3+1, 1), 3)), D5="Yearly", SUMIFS(Sales_Invoicing!L:L, Sales_Invoicing!B:B, ">="&DATE(YEAR(TODAY()), 1, 1), Sales_Invoicing!B:B, "<"&DATE(YEAR(TODAY())+1, 1, 1)), TRUE, SUM(Sales_Invoicing!L2:L100)) | J8: =_xludf.IFS(D5="Daily", SUMIFS(Sales_Invoicing!Q:Q, Sales_Invoicing!B:B, ">="&TODAY(), Sales_Invoicing!B:B, "<"&TODAY()+1), D5="Monthly", SUMIFS(Sales_Invoicing!Q:Q, Sales_Invoicing!B:B, ">="&DATE(YEAR(TODAY()), MONTH(TODAY()), 1), Sales_Invoicing!B:B, "<"&EDATE(DATE(YEAR(TODAY()), MONTH(TODAY()), 1), 1)), D5="Quarterly", SUMIFS(Sales_Invoicing!Q:Q, Sales_Invoicing!B:B, ">="&DATE(YEAR(TODAY()), INT((MONTH(TODAY())-1)/3)*3+1, 1), Sales_Invoicing!B:B, "<"&EDATE(DATE(YEAR(TODAY()), INT((MONTH(TODAY())-1)/3)*3+1, 1), 3)), D5="Yearly", SUMIFS(Sales_Invoicing!Q:Q, Sales_Invoicing!B:B, ">="&DATE(YEAR(TODAY()), 1, 1), Sales_Invoicing!B:B, "<"&DATE(YEAR(TODAY())+1, 1, 1)), TRUE, SUM(Sales_Invoicing!Q2:Q100)) | M8: =IFERROR(J8/F8, 0)
B10: ="Catalog: " & TEXT(COUNTA(Inventory_Master!A2:A100), "#,##0") & " Products" | F10: ="Orders: " & TEXT(_xludf.IFS(D5="Daily", COUNTIFS(Sales_Invoicing!B:B, ">="&TODAY(), Sales_Invoicing!B:B, "<"&TODAY()+1), D5="Monthly", COUNTIFS(Sales_Invoicing!B:B, ">="&DATE(YEAR(TODAY()), MONTH(TODAY()), 1), Sales_Invoicing!B:B, "<"&EDATE(DATE(YEAR(TODAY()), MONTH(TODAY()), 1), 1)), D5="Quarterly", COUNTIFS(Sales_Invoicing!B:B, ">="&DATE(YEAR(TODAY()), INT((MONTH(TODAY())-1)/3)*3+1, 1), Sales_Invoicing!B:B, "<"&EDATE(DATE(YEAR(TODAY()), INT((MONTH(TODAY())-1)/3)*3+1, 1), 3)), D5="Yearly", COUNTIFS(Sales_Invoicing!B:B, ">="&DATE(YEAR(TODAY()), 1, 1), Sales_Invoicing!B:B, "<"&DATE(YEAR(TODAY())+1, 1, 1)), TRUE, COUNTA(Sales_Invoicing!A2:A100)), "#,##0") & " Invoiced" | J10: Net Revenue After COGS | M10: =IF(M8>=0.2, "Healthy Margin (>20%)", "Moderate Margin (<20%)")
B12: 📅 MULTI-PERIOD SALES & PROFITABILITY BENCHMARK
B13: Timeframe Basis | C13: Orders Count | D13: Total Sales (₹) | E13: Cost of Goods (₹) | F13: Gross Profit (₹) | G13: Margin % | H13: Performance Status
B14: Daily (Today) | C14: =COUNTIFS(Sales_Invoicing!$B:$B, ">="&TODAY(), Sales_Invoicing!$B:$B, "<"&TODAY()+1) | D14: =SUMIFS(Sales_Invoicing!$L:$L, Sales_Invoicing!$B:$B, ">="&TODAY(), Sales_Invoicing!$B:$B, "<"&TODAY()+1) | E14: =SUMIFS(Sales_Invoicing!$P:$P, Sales_Invoicing!$B:$B, ">="&TODAY(), Sales_Invoicing!$B:$B, "<"&TODAY()+1) | F14: =D14-E14 | G14: =IFERROR(F14/D14, 0) | H14: =IF(D14=0, "No Sales Yet", IF(G14>=0.2, "🌟 High Margin", "⚠️ Low Margin"))
B15: Monthly (MTD) | C15: =COUNTIFS(Sales_Invoicing!$B:$B, ">="&DATE(YEAR(TODAY()), MONTH(TODAY()), 1), Sales_Invoicing!$B:$B, "<"&EDATE(DATE(YEAR(TODAY()), MONTH(TODAY()), 1), 1)) | D15: =SUMIFS(Sales_Invoicing!$L:$L, Sales_Invoicing!$B:$B, ">="&DATE(YEAR(TODAY()), MONTH(TODAY()), 1), Sales_Invoicing!$B:$B, "<"&EDATE(DATE(YEAR(TODAY()), MONTH(TODAY()), 1), 1)) | E15: =SUMIFS(Sales_Invoicing!$P:$P, Sales_Invoicing!$B:$B, ">="&DATE(YEAR(TODAY()), MONTH(TODAY()), 1), Sales_Invoicing!$B:$B, "<"&EDATE(DATE(YEAR(TODAY()), MONTH(TODAY()), 1), 1)) | F15: =D15-E15 | G15: =IFERROR(F15/D15, 0) | H15: =IF(D15=0, "No Sales Yet", IF(G15>=0.2, "🌟 Healthy Margin", "⚠️ Low Margin"))
B16: Quarterly (QTD) | C16: =COUNTIFS(Sales_Invoicing!$B:$B, ">="&DATE(YEAR(TODAY()), INT((MONTH(TODAY())-1)/3)*3+1, 1), Sales_Invoicing!$B:$B, "<"&EDATE(DATE(YEAR(TODAY()), INT((MONTH(TODAY())-1)/3)*3+1, 1), 3)) | D16: =SUMIFS(Sales_Invoicing!$L:$L, Sales_Invoicing!$B:$B, ">="&DATE(YEAR(TODAY()), INT((MONTH(TODAY())-1)/3)*3+1, 1), Sales_Invoicing!$B:$B, "<"&EDATE(DATE(YEAR(TODAY()), INT((MONTH(TODAY())-1)/3)*3+1, 1), 3)) | E16: =SUMIFS(Sales_Invoicing!$P:$P, Sales_Invoicing!$B:$B, ">="&DATE(YEAR(TODAY()), INT((MONTH(TODAY())-1)/3)*3+1, 1), Sales_Invoicing!$B:$B, "<"&EDATE(DATE(YEAR(TODAY()), INT((MONTH(TODAY())-1)/3)*3+1, 1), 3)) | F16: =D16-E16 | G16: =IFERROR(F16/D16, 0) | H16: =IF(D16=0, "No Sales Yet", IF(G16>=0.2, "🌟 Healthy Margin", "⚠️ Low Margin"))
B17: Yearly (YTD) | C17: =COUNTIFS(Sales_Invoicing!$B:$B, ">="&DATE(YEAR(TODAY()), 1, 1), Sales_Invoicing!$B:$B, "<"&DATE(YEAR(TODAY())+1, 1, 1)) | D17: =SUMIFS(Sales_Invoicing!$L:$L, Sales_Invoicing!$B:$B, ">="&DATE(YEAR(TODAY()), 1, 1), Sales_Invoicing!$B:$B, "<"&DATE(YEAR(TODAY())+1, 1, 1)) | E17: =SUMIFS(Sales_Invoicing!$P:$P, Sales_Invoicing!$B:$B, ">="&DATE(YEAR(TODAY()), 1, 1), Sales_Invoicing!$B:$B, "<"&DATE(YEAR(TODAY())+1, 1, 1)) | F17: =D17-E17 | G17: =IFERROR(F17/D17, 0) | H17: =IF(D17=0, "No Sales Yet", IF(G17>=0.2, "🌟 Healthy Margin", "⚠️ Low Margin"))
B19: 🏆 TOP SELLING PRODUCTS & PROFITABILITY PERFORMANCE
B20: Product / Item Name | C20: Units Sold | D20: Sales Revenue (₹) | E20: Cost of Goods (₹) | F20: Gross Profit (₹) | G20: Margin % | H20: Profitability Tier
B21: KAPPA TAPIOCA | C21: =SUMIF(Sales_Invoicing!$D:$D, B21, Sales_Invoicing!$F:$F) | D21: =SUMIF(Sales_Invoicing!$D:$D, B21, Sales_Invoicing!$L:$L) | E21: =SUMIF(Sales_Invoicing!$D:$D, B21, Sales_Invoicing!$P:$P) | F21: =D21-E21 | G21: =IFERROR(F21/D21, 0) | H21: =IF(G21>=0.25, "💎 High Margin", IF(G21>=0.15, "✅ Healthy", "⚠️ Thin Margin"))
B22: KERALA BANANA | C22: =SUMIF(Sales_Invoicing!$D:$D, B22, Sales_Invoicing!$F:$F) | D22: =SUMIF(Sales_Invoicing!$D:$D, B22, Sales_Invoicing!$L:$L) | E22: =SUMIF(Sales_Invoicing!$D:$D, B22, Sales_Invoicing!$P:$P) | F22: =D22-E22 | G22: =IFERROR(F22/D22, 0) | H22: =IF(G22>=0.25, "💎 High Margin", IF(G22>=0.15, "✅ Healthy", "⚠️ Thin Margin"))
B23: KPL COCONUT OIL 500GM | C23: =SUMIF(Sales_Invoicing!$D:$D, B23, Sales_Invoicing!$F:$F) | D23: =SUMIF(Sales_Invoicing!$D:$D, B23, Sales_Invoicing!$L:$L) | E23: =SUMIF(Sales_Invoicing!$D:$D, B23, Sales_Invoicing!$P:$P) | F23: =D23-E23 | G23: =IFERROR(F23/D23, 0) | H23: =IF(G23>=0.25, "💎 High Margin", IF(G23>=0.15, "✅ Healthy", "⚠️ Thin Margin"))
B24: IDAYAM NALLENNA BOTTLE 500GM | C24: =SUMIF(Sales_Invoicing!$D:$D, B24, Sales_Invoicing!$F:$F) | D24: =SUMIF(Sales_Invoicing!$D:$D, B24, Sales_Invoicing!$L:$L) | E24: =SUMIF(Sales_Invoicing!$D:$D, B24, Sales_Invoicing!$P:$P) | F24: =D24-E24 | G24: =IFERROR(F24/D24, 0) | H24: =IF(G24>=0.25, "💎 High Margin", IF(G24>=0.15, "✅ Healthy", "⚠️ Thin Margin"))
B25: KALAN | C25: =SUMIF(Sales_Invoicing!$D:$D, B25, Sales_Invoicing!$F:$F) | D25: =SUMIF(Sales_Invoicing!$D:$D, B25, Sales_Invoicing!$L:$L) | E25: =SUMIF(Sales_Invoicing!$D:$D, B25, Sales_Invoicing!$P:$P) | F25: =D25-E25 | G25: =IFERROR(F25/D25, 0) | H25: =IF(G25>=0.25, "💎 High Margin", IF(G25>=0.15, "✅ Healthy", "⚠️ Thin Margin"))
B26: TN SAMBAR RTE | C26: =SUMIF(Sales_Invoicing!$D:$D, B26, Sales_Invoicing!$F:$F) | D26: =SUMIF(Sales_Invoicing!$D:$D, B26, Sales_Invoicing!$L:$L) | E26: =SUMIF(Sales_Invoicing!$D:$D, B26, Sales_Invoicing!$P:$P) | F26: =D26-E26 | G26: =IFERROR(F26/D26, 0) | H26: =IF(G26>=0.25, "💎 High Margin", IF(G26>=0.15, "✅ Healthy", "⚠️ Thin Margin"))
